Metadata-Version: 2.1
Name: TimeComplex
Version: 0.0.1
Summary: Big O calculations for Time
Home-page: https://github.com/hodge-py/TimeComplex
Download-URL: https://github.com/hodge-py/TimeComplex/releases
Author: Karson Hodge
Author-email: khodge1@hotmail.com
License: Copyright
Keywords: BigO,Algorithm,Calculations
Classifier: Development Status :: 3 - Alpha
Classifier: Intended Audience :: Developers
Classifier: License :: Free for non-commercial use
Classifier: Operating System :: OS Independent
License-File: LICENSE.txt
Requires-Dist: numpy
Requires-Dist: pandas
Requires-Dist: scikit-learn
Requires-Dist: matplotlib
